loofah.py
loofah-0.2.0.dist-info/METADATA
loofah-0.2.0.dist-info/RECORD
loofah-0.2.0.dist-info/WHEEL
loofah-0.2.0.dist-info/entry_points.txt
loofah-0.2.0.dist-info/top_level.txt
