Metadata-Version: 2.1
Name: loofah
Version: 0.2.0
Summary: A pytest-based tool to list test fixtures declared but not used in a test
Home-page: https://github.com/steinnes/loofah
Author: Steinn Eldjarn Sigurdarson
Author-email: steinnes@gmail.com
Maintainer: Steinn Eldjarn Sigurdarson
Maintainer-email: steinnes@gmail.com
License: MIT
Platform: UNKNOWN
Classifier: Development Status :: 4 - Beta
Classifier: Framework :: Pytest
Classifier: Intended Audience :: Developers
Classifier: Topic :: Software Development :: Testing
Classifier: Programming Language :: Python
Classifier: Programming Language :: Python :: 2
Classifier: Programming Language :: Python :: 2.7
Classifier: Programming Language :: Python :: 3
Classifier: Programming Language :: Python :: 3.4
Classifier: Programming Language :: Python :: 3.5
Classifier: Programming Language :: Python :: 3.6
Classifier: Programming Language :: Python :: Implementation :: CPython
Classifier: Programming Language :: Python :: Implementation :: PyPy
Classifier: Operating System :: OS Independent
Classifier: License :: OSI Approved :: MIT License
Requires-Dist: pytest (>=3.1.1)
Requires-Dist: click (>=6.1)
Requires-Dist: mock (==2.0.0)
